cerebrumscanner/__init__.py
cerebrumscanner/database_manager.py
cerebrumscanner/image_processor.py
cerebrumscanner-0.0.6.dist-info/LICENSE
cerebrumscanner-0.0.6.dist-info/METADATA
cerebrumscanner-0.0.6.dist-info/WHEEL
cerebrumscanner-0.0.6.dist-info/top_level.txt
cerebrumscanner-0.0.6.dist-info/RECORD
