Metadata-Version: 2.1
Name: cerebrumscanner
Version: 0.0.6
Summary: Cerebrum Scanner Project
Home-page: https://gitlab.com/nekodu/cerebrumscanner/cerebrum-scanner
Author: Nekodu Technology
Author-email: info@nekodu.com
License: GNU GENERAL PUBLIC LICENSE
License-File: LICENSE
Requires-Dist: kivy
Requires-Dist: kivymd ==1.2.0
Requires-Dist: tqdm
Requires-Dist: bcrypt
Requires-Dist: pydicom
Requires-Dist: dcm2niix
Requires-Dist: dicom2nifti
Requires-Dist: SimpleITK
Requires-Dist: gestures4kivy
Requires-Dist: opencv-python
Requires-Dist: pymongo
Requires-Dist: dnspython
Requires-Dist: nibabel
Requires-Dist: kivy-deps.angle ; python_version >= "3.6" and sys_platform == "windows"
Requires-Dist: kivy-deps.gstreamer ; python_version >= "3.6" and sys_platform == "windows"
Requires-Dist: kivy-deps.glew ; python_version >= "3.6" and sys_platform == "windows"
Requires-Dist: kivy-deps.sdl2 ; python_version >= "3.6" and sys_platform == "windows"
